azurly/__init__.py
azurly/batch.py
azurly/storage.py
azurly/api/__init__.py
azurly/api/batch.py
azurly/api/storage.py
azurly-0.1.1.dist-info/LICENCE
azurly-0.1.1.dist-info/METADATA
azurly-0.1.1.dist-info/WHEEL
azurly-0.1.1.dist-info/top_level.txt
azurly-0.1.1.dist-info/RECORD
