Metadata-Version: 2.1
Name: azurly
Version: 0.1.1
Summary: A combined CDK and API package for Microsoft Azure
Author: Max Snoodijk
Requires-Python: >=3.8
License-File: LICENCE
Requires-Dist: requests >=2.28.0
